Metadata-Version: 2.1
Name: odoo13-addon-hr-employee-service-contract
Version: 13.0.1.0.1
Summary: Employee service information & duration based on employee's contracts
Home-page: https://github.com/OCA/hr
Author: CorporateHub, Odoo Community Association (OCA)
Author-email: support@odoo-community.org
License: AGPL-3
Platform: UNKNOWN
Classifier: Programming Language :: Python
Classifier: Framework :: Odoo
Classifier: Framework :: Odoo :: 13.0
Classifier: License :: OSI Approved :: GNU Affero General Public License v3
Requires-Python: >=3.5
Requires-Dist: odoo13-addon-hr-employee-service
Requires-Dist: odoo (<13.1dev,>=13.0a)
Requires-Dist: python-dateutil
